{
  "items": [
    {
      "isBetween": true,
      "title": "Team over <span class='experience__title-span'>17</span> <span class='experience__title-span'>years</span> of experience",
      "text": [
        {
          "paragraph": "Developing the business projects of our Clients, GEM Expo exports its services to the most prestigious exhibition centers of the World and offers its Clients a comprehensive service around the World at the highest professional level"
        }
      ],
      "picture": {
        "sources": {
          "mobile": [
            "./assets/images/exp375_1.png",
            "./assets/images/exp375_1.png"
          ],
          "tablet": [
            "./assets/images/exp768_1.png",
            "./assets/images/exp768_1.png"
          ],
          "desktop": [
            "./assets/images/exp_1.png",
            "./assets/images/exp_1.webp"
          ],
          "alt": "exp__img1"
        }
      }
    },
    {
      "text": [
        {
          "paragraph": "We are ready to develop and increase the success of our Clients together in exhibition, advertising,expo and event projects, which are based on a strong team of professionals, ambitious goals, modern technologies, where our satisfied Clients are our main motivation."
        },
        {
          "paragraph": "We will be glad to become your strategic Partner for Expo and Event projects in Russia."
        }
      ],
      "picture": {
        "sources": {
          "mobile": [
            "./assets/images/exp375_2.png",
            "./assets/images/exp375_2.webp"
          ],
          "tablet": [
            "./assets/images/exp768_2.png",
            "./assets/images/exp768_2.webp"
          ],
          "desktop": [
            "./assets/images/exp_2.png",
            "./assets/images/exp_2.webp"
          ]
        },
        "alt": "exp__img2"
      }
    }
  ]
}