{
	"product": {
		"map": true,
		"items": [
			{
				"title": "Первый продукт",
				"content": "Описание первого продукта",
				"address": "Адрес первого продута",
				"mapPoint": {
					"balloonHeader": "Первое место",
					"coords": [55.76, 37.64],
					"balloonBody": "Содержимое первого места",
					"ballonFooter": "footer первого места",
					"hint": "hint первого места"
				}
			},
			{
				"title": "Второй продукт",
				"content": "Описание второго продукта",
				"address": "Адрес второго продута",
				"mapPoint": {
					"balloonHeader": "Второе место",
					"coords": [55.76, 37.65],
					"balloonBody": "Содержимое второго места",
					"ballonFooter": "footer второго места",
					"hint": "hint второго места"
				}
			},
			{
				"title": "Третий продукт",
				"content": "Описание третьего продукта",
				"address": "Адрес третьего продута",
				"mapPoint": {
					"balloonHeader": "Третье место",
					"coords": [55.76, 37.66],
					"balloonBody": "Содержимое третьего места",
					"ballonFooter": "footer третьего места",
					"hint": "hint третьего места"
				}
			}
		]
	}
}